AircrackNgJiaochengJiWendangBufen/README.md
AircrackNgJiaochengJiWendangBufen/__init__.py
AircrackNgJiaochengJiWendangBufen/__main__.py
AircrackNgJiaochengJiWendangBufen/file.epub
AircrackNgJiaochengJiWendangBufen/index.html
AircrackNgJiaochengJiWendangBufen/css/__init__.py
AircrackNgJiaochengJiWendangBufen/css/annotations.css
AircrackNgJiaochengJiWendangBufen/css/main.css
AircrackNgJiaochengJiWendangBufen/css/normalize.css
AircrackNgJiaochengJiWendangBufen/css/popup.css
AircrackNgJiaochengJiWendangBufen/font/__init__.py
AircrackNgJiaochengJiWendangBufen/font/fontello.eot
AircrackNgJiaochengJiWendangBufen/font/fontello.svg
AircrackNgJiaochengJiWendangBufen/font/fontello.ttf
AircrackNgJiaochengJiWendangBufen/font/fontello.woff
AircrackNgJiaochengJiWendangBufen/img/__init__.py
AircrackNgJiaochengJiWendangBufen/img/annotator-glyph-sprite.png
AircrackNgJiaochengJiWendangBufen/img/annotator-icon-sprite.png
AircrackNgJiaochengJiWendangBufen/img/apple-touch-icon.png
AircrackNgJiaochengJiWendangBufen/img/cancelfullscreen.png
AircrackNgJiaochengJiWendangBufen/img/close.png
AircrackNgJiaochengJiWendangBufen/img/fullscreen.png
AircrackNgJiaochengJiWendangBufen/img/loader.gif
AircrackNgJiaochengJiWendangBufen/img/menu-icon.png
AircrackNgJiaochengJiWendangBufen/img/save.png
AircrackNgJiaochengJiWendangBufen/img/saved.png
AircrackNgJiaochengJiWendangBufen/img/settings-s.png
AircrackNgJiaochengJiWendangBufen/img/settings.png
AircrackNgJiaochengJiWendangBufen/img/star.png
AircrackNgJiaochengJiWendangBufen/js/__init__.py
AircrackNgJiaochengJiWendangBufen/js/epub.js
AircrackNgJiaochengJiWendangBufen/js/epub.min.js
AircrackNgJiaochengJiWendangBufen/js/epub.min.map
AircrackNgJiaochengJiWendangBufen/js/hooks.min.js
AircrackNgJiaochengJiWendangBufen/js/hooks.min.map
AircrackNgJiaochengJiWendangBufen/js/reader.js
AircrackNgJiaochengJiWendangBufen/js/reader.js.map
AircrackNgJiaochengJiWendangBufen/js/reader.min.js
AircrackNgJiaochengJiWendangBufen/js/reader.min.map
aircrack_ng_jiaocheng_ji_wendang_bufen-2024.3.1.0.dist-info/METADATA
aircrack_ng_jiaocheng_ji_wendang_bufen-2024.3.1.0.dist-info/WHEEL
aircrack_ng_jiaocheng_ji_wendang_bufen-2024.3.1.0.dist-info/entry_points.txt
aircrack_ng_jiaocheng_ji_wendang_bufen-2024.3.1.0.dist-info/top_level.txt
aircrack_ng_jiaocheng_ji_wendang_bufen-2024.3.1.0.dist-info/RECORD
